__init__.py
vision.py
regia_ai_sdk-0.7.2.dist-info/METADATA
regia_ai_sdk-0.7.2.dist-info/WHEEL
regia_ai_sdk-0.7.2.dist-info/top_level.txt
regia_ai_sdk-0.7.2.dist-info/RECORD
