Metadata-Version: 2.4
Name: regia-ai-sdk
Version: 0.7.2
Summary: Add your description here
Requires-Python: >=3.13
Requires-Dist: pydantic>=2.11.4
Requires-Dist: requests>=2.32.3
